asyncoinpayments/__init__.py
asyncoinpayments/coinpayments.py
asyncoinpayments/errors.py
asyncoinpayments/utils.py
asyncoinpayments-0.0.8a0.dist-info/LICENSE.txt
asyncoinpayments-0.0.8a0.dist-info/METADATA
asyncoinpayments-0.0.8a0.dist-info/WHEEL
asyncoinpayments-0.0.8a0.dist-info/top_level.txt
asyncoinpayments-0.0.8a0.dist-info/RECORD
