Metadata-Version: 2.1
Name: asyncoinpayments
Version: 0.0.8a0
Summary: Python Asynchronous Wrapper of the CoinPayments API
Author-email: flalugli <flalugli.dev@gmail.com>
License: Apache License 2.0
Project-URL: Homepage, https://github.com/flalugli/asyncoinpayments
Keywords: python,crypto,cryptocurrency,payment gateway,async,aiohttp
Classifier: Development Status :: 1 - Planning
Classifier: Intended Audience :: Developers
Classifier: Programming Language :: Python :: 3
Classifier: Operating System :: OS Independent
Requires-Python: >=3.8
License-File: LICENSE.txt
Requires-Dist: aiohttp
Requires-Dist: tenacity
